wala/__init__.py
wala/app.py
wala/app_proxied.py
wala/loadenv.py
wala/static/script.js
wala/static/style.css
wala/templates/machines.html
wala-0.3.0.dist-info/WHEEL
wala-0.3.0.dist-info/METADATA
wala-0.3.0.dist-info/RECORD
