Metadata-Version: 2.1
Name: wala
Version: 0.3.0
Summary: Web interface to execute scripts and get status feedback.
Author: Adnn
Requires-Python: >=3.7
Classifier: Programming Language :: Python :: 3
Classifier: License :: OSI Approved :: MIT License
Classifier: Operating System :: OS Independent
Requires-Dist: flask
Project-URL: Homepage, https://github.com/Adnn/wala
Project-URL: Issues, https://github.com/Adnn/wala/issues
